Metadata-Version: 2.1
Name: approxmath
Version: 2.0.0
Summary: Fast approximate math functions: log, exp, sin, cos
Home-page: https://github.com/brendanashworth/approxmath
Author: Brendan Ashworth
Author-email: brendan.ashworth@me.com
License: UNKNOWN
Platform: UNKNOWN
License-File: LICENSE
